MANIFEST.in
README.md
requirements.txt
setup.py
flango/__init__.py
flango/_request.py
flango/app.py
flango/middleware.py
flango/templating.py
flango/urlresolvers.py
flango.egg-info/PKG-INFO
flango.egg-info/SOURCES.txt
flango.egg-info/dependency_links.txt
flango.egg-info/requires.txt
flango.egg-info/top_level.txt
test/test_flango.py