Metadata-Version: 2.1
Name: flango
Version: 0.0.2
Summary: Flask-like interface for Django
Home-page: https://github.com/theY4Kman/flango
Author: Zach "theY4Kman" Kanzler
Author-email: they4kman@gmail.com
License: MIT
Platform: UNKNOWN
